UrDaddy/__init__.py
urdaddy-1.0.0.dist-info/METADATA
urdaddy-1.0.0.dist-info/WHEEL
urdaddy-1.0.0.dist-info/entry_points.txt
urdaddy-1.0.0.dist-info/top_level.txt
urdaddy-1.0.0.dist-info/RECORD
