Metadata-Version: 2.1
Name: urdaddy
Version: 1.0.0
Summary: ur mom
Classifier: Programming Language :: Python
Classifier: Programming Language :: Python :: 3
Requires-Python: >=3.9
Requires-Dist: selenium (>=4.3.0)
